vlt/__init__.py
vlt/app.py
vlt/cmd_reader.py
vlt/constants.py
vlt/encryption.py
vlt/help_menu.py
vlt/help_text.md
vlt/settings.py
vlt/storage.py
vlt-0.0.7.dist-info/LICENSE.txt
vlt-0.0.7.dist-info/METADATA
vlt-0.0.7.dist-info/WHEEL
vlt-0.0.7.dist-info/entry_points.txt
vlt-0.0.7.dist-info/top_level.txt
vlt-0.0.7.dist-info/RECORD
