Metadata-Version: 2.1
Name: vlt
Version: 0.0.7
Summary: a python-based password manager
Home-page: https://github.com/1mikegrn/vlt
Author: Michael Green
Author-email: 1mikegrn@gmail.com
License: UNKNOWN
Platform: UNKNOWN
Classifier: Development Status :: 3 - Alpha
Classifier: License :: OSI Approved :: GNU Lesser General Public License v3 (LGPLv3)
Classifier: Operating System :: OS Independent
Classifier: Programming Language :: Python :: 3
Classifier: Programming Language :: Python :: 3.6
Classifier: Programming Language :: Python :: 3.7
Classifier: Programming Language :: Python :: 3.8
Classifier: Programming Language :: Python :: 3.9
Classifier: Topic :: Software Development :: Libraries :: Python Modules
Requires-Python: >=3.6
Requires-Dist: cryptography (>=3.0.0)
Requires-Dist: pandas (>=1.0.0)
Requires-Dist: pyperclip (>=1.0)
